LICENSE
MANIFEST.in
README.rst
requirements.txt
setup.py
sonopod.py
sonopod.egg-info/PKG-INFO
sonopod.egg-info/SOURCES.txt
sonopod.egg-info/dependency_links.txt
sonopod.egg-info/requires.txt
sonopod.egg-info/top_level.txt