Metadata-Version: 1.1
Name: sonopod
Version: 0.1.2
Summary:  sonopod is a commandline tool for playing podcasts through Sonos speakers 
Home-page: https://github.com/havardgulldahl/sonopod
Author: <havard@gulldahl.no>
Author-email: <havard@gulldahl.no>
License: GPLv3 License
Platform: UNKNOWN
Classifier: Intended Audience :: Developers
Classifier: Intended Audience :: End Users/Desktop
Classifier: License :: OSI Approved :: GNU General Public License v3 or later (GPLv3+)
Classifier: Operating System :: OS Independent
Classifier: Operating System :: Microsoft :: Windows
Classifier: Operating System :: POSIX
Classifier: Operating System :: POSIX :: Linux
Classifier: Operating System :: MacOS :: MacOS X
Classifier: Environment :: Console
Classifier: Topic :: Multimedia :: Sound/Audio :: Players
Classifier: Programming Language :: Python :: 2.7
Classifier: Programming Language :: Python :: Implementation :: CPython
Classifier: Programming Language :: Python :: Implementation :: PyPy
Classifier: Topic :: Utilities
